[
{"train_mad": {"data": 2.7863652320732055, "label": "train_mad", "epoch": 0, "counter": 0}},
{"train_mse": {"data": 35.68433118971311, "label": "train_mse", "epoch": 0, "counter": 0}},
{"train_mape": {"data": 132.65444821061493, "label": "train_mape", "epoch": 0, "counter": 0}},
{"train_msle": {"data": 1.6087385470043274, "label": "train_msle", "epoch": 0, "counter": 0}},
{"train_r2": {"data": 0.026693856022973583, "label": "train_r2", "epoch": 0, "counter": 0}},
{"train_kappa": {"data": 0.27337891014855953, "label": "train_kappa", "epoch": 0, "counter": 0}},
{"val_mad": {"data": 2.6154796066148176, "label": "val_mad", "epoch": 0, "counter": 0}},
{"val_mse": {"data": 57.54032794002451, "label": "val_mse", "epoch": 0, "counter": 0}},
{"val_mape": {"data": 122.79151059305815, "label": "val_mape", "epoch": 0, "counter": 0}},
{"val_msle": {"data": 1.375732886030686, "label": "val_msle", "epoch": 0, "counter": 0}},
{"val_r2": {"data": 0.0670887725956687, "label": "val_r2", "epoch": 0, "counter": 0}},
{"val_kappa": {"data": 0.3399104045834982, "label": "val_kappa", "epoch": 0, "counter": 0}},
{"train_mad": {"data": 2.637813013441262, "label": "train_mad", "epoch": 1, "counter": 1}},
{"train_mse": {"data": 32.71461204600895, "label": "train_mse", "epoch": 1, "counter": 1}},
{"train_mape": {"data": 121.64798175157914, "label": "train_mape", "epoch": 1, "counter": 1}},
{"train_msle": {"data": 1.434706967675726, "label": "train_msle", "epoch": 1, "counter": 1}},
{"train_r2": {"data": 0.1076942781154212, "label": "train_r2", "epoch": 1, "counter": 1}},
{"train_kappa": {"data": 0.3366148580307249, "label": "train_kappa", "epoch": 1, "counter": 1}},
{"val_mad": {"data": 2.516957532392148, "label": "val_mad", "epoch": 1, "counter": 1}},
{"val_mse": {"data": 55.48094513813203, "label": "val_mse", "epoch": 1, "counter": 1}},
{"val_mape": {"data": 117.22339015486708, "label": "val_mape", "epoch": 1, "counter": 1}},
{"val_msle": {"data": 1.2713376478830052, "label": "val_msle", "epoch": 1, "counter": 1}},
{"val_r2": {"data": 0.10047789994668799, "label": "val_r2", "epoch": 1, "counter": 1}},
{"val_kappa": {"data": 0.4032617341398226, "label": "val_kappa", "epoch": 1, "counter": 1}},
{"train_mad": {"data": 2.5755900182391582, "label": "train_mad", "epoch": 2, "counter": 2}},
{"train_mse": {"data": 31.598346125881456, "label": "train_mse", "epoch": 2, "counter": 2}},
{"train_mape": {"data": 118.44137442870102, "label": "train_mape", "epoch": 2, "counter": 2}},
{"train_msle": {"data": 1.3710881580173797, "label": "train_msle", "epoch": 2, "counter": 2}},
{"train_r2": {"data": 0.1381409319309609, "label": "train_r2", "epoch": 2, "counter": 2}},
{"train_kappa": {"data": 0.36641899876889616, "label": "train_kappa", "epoch": 2, "counter": 2}},
{"val_mad": {"data": 2.4486764581544667, "label": "val_mad", "epoch": 2, "counter": 2}},
{"val_mse": {"data": 54.20340664363029, "label": "val_mse", "epoch": 2, "counter": 2}},
{"val_mape": {"data": 113.24873288054913, "label": "val_mape", "epoch": 2, "counter": 2}},
{"val_msle": {"data": 1.2097175933026303, "label": "val_msle", "epoch": 2, "counter": 2}},
{"val_r2": {"data": 0.12119085115204387, "label": "val_r2", "epoch": 2, "counter": 2}},
{"val_kappa": {"data": 0.43627829980530886, "label": "val_kappa", "epoch": 2, "counter": 2}},
{"train_mad": {"data": 2.522352724839053, "label": "train_mad", "epoch": 3, "counter": 3}},
{"train_mse": {"data": 30.58087260177718, "label": "train_mse", "epoch": 3, "counter": 3}},
{"train_mape": {"data": 115.95436650416941, "label": "train_mape", "epoch": 3, "counter": 3}},
{"train_msle": {"data": 1.3227062786765225, "label": "train_msle", "epoch": 3, "counter": 3}},
{"train_r2": {"data": 0.16589297881898368, "label": "train_r2", "epoch": 3, "counter": 3}},
{"train_kappa": {"data": 0.3916353878301112, "label": "train_kappa", "epoch": 3, "counter": 3}},
{"val_mad": {"data": 2.3957634510908243, "label": "val_mad", "epoch": 3, "counter": 3}},
{"val_mse": {"data": 52.952447637547316, "label": "val_mse", "epoch": 3, "counter": 3}},
{"val_mape": {"data": 111.91563676821316, "label": "val_mape", "epoch": 3, "counter": 3}},
{"val_msle": {"data": 1.167219134107402, "label": "val_msle", "epoch": 3, "counter": 3}},
{"val_r2": {"data": 0.14147286454296149, "label": "val_r2", "epoch": 3, "counter": 3}},
{"val_kappa": {"data": 0.466615329040324, "label": "val_kappa", "epoch": 3, "counter": 3}},
{"train_mad": {"data": 2.486601794357142, "label": "train_mad", "epoch": 4, "counter": 4}},
{"train_mse": {"data": 29.89734331386676, "label": "train_mse", "epoch": 4, "counter": 4}},
{"train_mape": {"data": 113.77208949946413, "label": "train_mape", "epoch": 4, "counter": 4}},
{"train_msle": {"data": 1.2867966441014214, "label": "train_msle", "epoch": 4, "counter": 4}},
{"train_r2": {"data": 0.18453654683135645, "label": "train_r2", "epoch": 4, "counter": 4}},
{"train_kappa": {"data": 0.408864409745487, "label": "train_kappa", "epoch": 4, "counter": 4}},
{"val_mad": {"data": 2.358996641361702, "label": "val_mad", "epoch": 4, "counter": 4}},
{"val_mse": {"data": 52.27696272717792, "label": "val_mse", "epoch": 4, "counter": 4}},
{"val_mape": {"data": 108.68428776407254, "label": "val_mape", "epoch": 4, "counter": 4}},
{"val_msle": {"data": 1.1331418535049114, "label": "val_msle", "epoch": 4, "counter": 4}},
{"val_r2": {"data": 0.15242461750277525, "label": "val_r2", "epoch": 4, "counter": 4}},
{"val_kappa": {"data": 0.48488009846932445, "label": "val_kappa", "epoch": 4, "counter": 4}},
{"train_mad": {"data": 2.4613255983129365, "label": "train_mad", "epoch": 5, "counter": 5}},
{"train_mse": {"data": 29.471690353476138, "label": "train_mse", "epoch": 5, "counter": 5}},
{"train_mape": {"data": 111.86399491409355, "label": "train_mape", "epoch": 5, "counter": 5}},
{"train_msle": {"data": 1.2611672160998053, "label": "train_msle", "epoch": 5, "counter": 5}},
{"train_r2": {"data": 0.1961464223071684, "label": "train_r2", "epoch": 5, "counter": 5}},
{"train_kappa": {"data": 0.42084143288538534, "label": "train_kappa", "epoch": 5, "counter": 5}},
{"val_mad": {"data": 2.3391605908987936, "label": "val_mad", "epoch": 5, "counter": 5}},
{"val_mse": {"data": 51.464134080137406, "label": "val_mse", "epoch": 5, "counter": 5}},
{"val_mape": {"data": 108.83044073309318, "label": "val_mape", "epoch": 5, "counter": 5}},
{"val_msle": {"data": 1.1117948533450168, "label": "val_msle", "epoch": 5, "counter": 5}},
{"val_r2": {"data": 0.16560314807302767, "label": "val_r2", "epoch": 5, "counter": 5}},
{"val_kappa": {"data": 0.5015865027607584, "label": "val_kappa", "epoch": 5, "counter": 5}},
{"train_mad": {"data": 2.4381375071295777, "label": "train_mad", "epoch": 6, "counter": 6}},
{"train_mse": {"data": 29.062914433884103, "label": "train_mse", "epoch": 6, "counter": 6}},
{"train_mape": {"data": 110.22651043521702, "label": "train_mape", "epoch": 6, "counter": 6}},
{"train_msle": {"data": 1.2380188456929302, "label": "train_msle", "epoch": 6, "counter": 6}},
{"train_r2": {"data": 0.20729596892284052, "label": "train_r2", "epoch": 6, "counter": 6}},
{"train_kappa": {"data": 0.43224113832498356, "label": "train_kappa", "epoch": 6, "counter": 6}},
{"val_mad": {"data": 2.319241263257186, "label": "val_mad", "epoch": 6, "counter": 6}},
{"val_mse": {"data": 50.682042622136436, "label": "val_mse", "epoch": 6, "counter": 6}},
{"val_mape": {"data": 109.40003418022819, "label": "val_mape", "epoch": 6, "counter": 6}},
{"val_msle": {"data": 1.0942110090119637, "label": "val_msle", "epoch": 6, "counter": 6}},
{"val_r2": {"data": 0.17828333131401697, "label": "val_r2", "epoch": 6, "counter": 6}},
{"val_kappa": {"data": 0.5148073496548109, "label": "val_kappa", "epoch": 6, "counter": 6}},
{"train_mad": {"data": 2.417222289180225, "label": "train_mad", "epoch": 7, "counter": 7}},
{"train_mse": {"data": 28.726046109306342, "label": "train_mse", "epoch": 7, "counter": 7}},
{"train_mape": {"data": 108.76630986208811, "label": "train_mape", "epoch": 7, "counter": 7}},
{"train_msle": {"data": 1.2173244302500676, "label": "train_msle", "epoch": 7, "counter": 7}},
{"train_r2": {"data": 0.21648420362113574, "label": "train_r2", "epoch": 7, "counter": 7}},
{"train_kappa": {"data": 0.44254528224574496, "label": "train_kappa", "epoch": 7, "counter": 7}},
{"val_mad": {"data": 2.3049722993382002, "label": "val_mad", "epoch": 7, "counter": 7}},
{"val_mse": {"data": 50.49279113858807, "label": "val_mse", "epoch": 7, "counter": 7}},
{"val_mape": {"data": 105.99732510127686, "label": "val_mape", "epoch": 7, "counter": 7}},
{"val_msle": {"data": 1.074012258861312, "label": "val_msle", "epoch": 7, "counter": 7}},
{"val_r2": {"data": 0.1813516981469141, "label": "val_r2", "epoch": 7, "counter": 7}},
{"val_kappa": {"data": 0.5192763264016766, "label": "val_kappa", "epoch": 7, "counter": 7}},
{"train_mad": {"data": 2.399233981156794, "label": "train_mad", "epoch": 8, "counter": 8}},
{"train_mse": {"data": 28.441705402727987, "label": "train_mse", "epoch": 8, "counter": 8}},
{"train_mape": {"data": 107.5128350517738, "label": "train_mape", "epoch": 8, "counter": 8}},
{"train_msle": {"data": 1.2001683438603006, "label": "train_msle", "epoch": 8, "counter": 8}},
{"train_r2": {"data": 0.22423972397050584, "label": "train_r2", "epoch": 8, "counter": 8}},
{"train_kappa": {"data": 0.45130294378140756, "label": "train_kappa", "epoch": 8, "counter": 8}},
{"val_mad": {"data": 2.296141976061451, "label": "val_mad", "epoch": 8, "counter": 8}},
{"val_mse": {"data": 49.93056588131738, "label": "val_mse", "epoch": 8, "counter": 8}},
{"val_mape": {"data": 109.3250662104092, "label": "val_mape", "epoch": 8, "counter": 8}},
{"val_msle": {"data": 1.0716965818833615, "label": "val_msle", "epoch": 8, "counter": 8}},
{"val_r2": {"data": 0.1904671528830224, "label": "val_r2", "epoch": 8, "counter": 8}},
{"val_kappa": {"data": 0.5277857656322875, "label": "val_kappa", "epoch": 8, "counter": 8}},
{"train_mad": {"data": 2.376861960600458, "label": "train_mad", "epoch": 9, "counter": 9}},
{"train_mse": {"data": 28.051958936854618, "label": "train_mse", "epoch": 9, "counter": 9}},
{"train_mape": {"data": 106.19055545715639, "label": "train_mape", "epoch": 9, "counter": 9}},
{"train_msle": {"data": 1.181954370464903, "label": "train_msle", "epoch": 9, "counter": 9}},
{"train_r2": {"data": 0.23487023369790228, "label": "train_r2", "epoch": 9, "counter": 9}},
{"train_kappa": {"data": 0.46118304008809274, "label": "train_kappa", "epoch": 9, "counter": 9}},
{"val_mad": {"data": 2.294565595517871, "label": "val_mad", "epoch": 9, "counter": 9}},
{"val_mse": {"data": 49.520343455121846, "label": "val_mse", "epoch": 9, "counter": 9}},
{"val_mape": {"data": 109.8101764169724, "label": "val_mape", "epoch": 9, "counter": 9}},
{"val_msle": {"data": 1.059940219614608, "label": "val_msle", "epoch": 9, "counter": 9}},
{"val_r2": {"data": 0.19711815959139134, "label": "val_r2", "epoch": 9, "counter": 9}},
{"val_kappa": {"data": 0.5354948031300232, "label": "val_kappa", "epoch": 9, "counter": 9}},
{"train_mad": {"data": 2.3628504456686508, "label": "train_mad", "epoch": 10, "counter": 10}},
{"train_mse": {"data": 27.807238019815316, "label": "train_mse", "epoch": 10, "counter": 10}},
{"train_mape": {"data": 104.96788716676649, "label": "train_mape", "epoch": 10, "counter": 10}},
{"train_msle": {"data": 1.1666510865813888, "label": "train_msle", "epoch": 10, "counter": 10}},
{"train_r2": {"data": 0.2415451065110632, "label": "train_r2", "epoch": 10, "counter": 10}},
{"train_kappa": {"data": 0.4681661872434202, "label": "train_kappa", "epoch": 10, "counter": 10}},
{"val_mad": {"data": 2.2960733823953605, "label": "val_mad", "epoch": 10, "counter": 10}},
{"val_mse": {"data": 49.38318960022409, "label": "val_mse", "epoch": 10, "counter": 10}},
{"val_mape": {"data": 108.37576380709453, "label": "val_mape", "epoch": 10, "counter": 10}},
{"val_msle": {"data": 1.0487570880190196, "label": "val_msle", "epoch": 10, "counter": 10}},
{"val_r2": {"data": 0.19934185861600007, "label": "val_r2", "epoch": 10, "counter": 10}},
{"val_kappa": {"data": 0.539754738572805, "label": "val_kappa", "epoch": 10, "counter": 10}},
{"train_mad": {"data": 2.348691689155213, "label": "train_mad", "epoch": 11, "counter": 11}},
{"train_mse": {"data": 27.523317409096872, "label": "train_mse", "epoch": 11, "counter": 11}},
{"train_mape": {"data": 103.93261262926758, "label": "train_mape", "epoch": 11, "counter": 11}},
{"train_msle": {"data": 1.1533091016717445, "label": "train_msle", "epoch": 11, "counter": 11}},
{"train_r2": {"data": 0.24928916855736638, "label": "train_r2", "epoch": 11, "counter": 11}},
{"train_kappa": {"data": 0.47433425485136793, "label": "train_kappa", "epoch": 11, "counter": 11}},
{"val_mad": {"data": 2.3046953373029915, "label": "val_mad", "epoch": 11, "counter": 11}},
{"val_mse": {"data": 49.15491535444772, "label": "val_mse", "epoch": 11, "counter": 11}},
{"val_mape": {"data": 108.62440126619602, "label": "val_mape", "epoch": 11, "counter": 11}},
{"val_msle": {"data": 1.0416394195776155, "label": "val_msle", "epoch": 11, "counter": 11}},
{"val_r2": {"data": 0.20304290820045856, "label": "val_r2", "epoch": 11, "counter": 11}},
{"val_kappa": {"data": 0.5438313564107786, "label": "val_kappa", "epoch": 11, "counter": 11}},
{"train_mad": {"data": 2.3341021026005633, "label": "train_mad", "epoch": 12, "counter": 12}},
{"train_mse": {"data": 27.245584663765197, "label": "train_mse", "epoch": 12, "counter": 12}},
{"train_mape": {"data": 103.06742288499724, "label": "train_mape", "epoch": 12, "counter": 12}},
{"train_msle": {"data": 1.140539329820811, "label": "train_msle", "epoch": 12, "counter": 12}},
{"train_r2": {"data": 0.2568644537988859, "label": "train_r2", "epoch": 12, "counter": 12}},
{"train_kappa": {"data": 0.4802793565907153, "label": "train_kappa", "epoch": 12, "counter": 12}},
{"val_mad": {"data": 2.3231678488965932, "label": "val_mad", "epoch": 12, "counter": 12}},
{"val_mse": {"data": 49.20638046295091, "label": "val_mse", "epoch": 12, "counter": 12}},
{"val_mape": {"data": 108.86966820764383, "label": "val_mape", "epoch": 12, "counter": 12}},
{"val_msle": {"data": 1.0338920755334524, "label": "val_msle", "epoch": 12, "counter": 12}},
{"val_r2": {"data": 0.20220849555004328, "label": "val_r2", "epoch": 12, "counter": 12}},
{"val_kappa": {"data": 0.5509588497075488, "label": "val_kappa", "epoch": 12, "counter": 12}},
{"train_mad": {"data": 2.322690086078556, "label": "train_mad", "epoch": 13, "counter": 13}},
{"train_mse": {"data": 27.162505271329962, "label": "train_mse", "epoch": 13, "counter": 13}},
{"train_mape": {"data": 102.14672914524745, "label": "train_mape", "epoch": 13, "counter": 13}},
{"train_msle": {"data": 1.1291895760928727, "label": "train_msle", "epoch": 13, "counter": 13}},
{"train_r2": {"data": 0.2591304815034601, "label": "train_r2", "epoch": 13, "counter": 13}},
{"train_kappa": {"data": 0.48605628900678743, "label": "train_kappa", "epoch": 13, "counter": 13}},
{"val_mad": {"data": 2.3378050154894354, "label": "val_mad", "epoch": 13, "counter": 13}},
{"val_mse": {"data": 49.354692888989206, "label": "val_mse", "epoch": 13, "counter": 13}},
{"val_mape": {"data": 109.40255612565784, "label": "val_mape", "epoch": 13, "counter": 13}},
{"val_msle": {"data": 1.0356084687256017, "label": "val_msle", "epoch": 13, "counter": 13}},
{"val_r2": {"data": 0.1998038806935044, "label": "val_r2", "epoch": 13, "counter": 13}},
{"val_kappa": {"data": 0.5501221604105604, "label": "val_kappa", "epoch": 13, "counter": 13}},
{"train_mad": {"data": 2.3086079815003444, "label": "train_mad", "epoch": 14, "counter": 14}},
{"train_mse": {"data": 26.852759264587622, "label": "train_mse", "epoch": 14, "counter": 14}},
{"train_mape": {"data": 101.32541105093497, "label": "train_mape", "epoch": 14, "counter": 14}},
{"train_msle": {"data": 1.1179482138010859, "label": "train_msle", "epoch": 14, "counter": 14}},
{"train_r2": {"data": 0.2675789428136044, "label": "train_r2", "epoch": 14, "counter": 14}},
{"train_kappa": {"data": 0.4911872690130301, "label": "train_kappa", "epoch": 14, "counter": 14}},
{"val_mad": {"data": 2.3249602057679026, "label": "val_mad", "epoch": 14, "counter": 14}},
{"val_mse": {"data": 49.209730779846055, "label": "val_mse", "epoch": 14, "counter": 14}},
{"val_mape": {"data": 108.67116195025739, "label": "val_mape", "epoch": 14, "counter": 14}},
{"val_msle": {"data": 1.0239102022240436, "label": "val_msle", "epoch": 14, "counter": 14}},
{"val_r2": {"data": 0.2021541762863417, "label": "val_r2", "epoch": 14, "counter": 14}},
{"val_kappa": {"data": 0.5552316473340312, "label": "val_kappa", "epoch": 14, "counter": 14}}
]